MANIFEST.in
setup.py
blueberry/LICENSE
blueberry/__init__.py
blueberry/configuration.py
blueberry/deploy.py
blueberry/log.py
blueberry/reloader.py
blueberry.egg-info/PKG-INFO
blueberry.egg-info/SOURCES.txt
blueberry.egg-info/dependency_links.txt
blueberry.egg-info/not-zip-safe
blueberry.egg-info/requires.txt
blueberry.egg-info/top_level.txt
blueberry/controllers/__init__.py
blueberry/controllers/core.py
blueberry/controllers/util.py
blueberry/decorators/__init__.py
blueberry/decorators/rest.py
blueberry/tests/__init__.py
blueberry/tests/test_object_proxy.py
blueberry/utils/__init__.py
blueberry/utils/daemonize.py
blueberry/utils/routing.py
blueberry/web/__init__.py
blueberry/web/templating.py
blueberry/wsgiserver/LICENSE.txt
blueberry/wsgiserver/__init__.py