Metadata-Version: 1.0
Name: blueberry
Version: 0.2
Summary: Blueberry Web Framework
Home-page: http://code.google.com/p/blueberrypy
Author: David Reynolds
Author-email: david@alwaysmovefast.com
License: BSD
Platform: UNKNOWN
